sslcontext/__init__.py
sslcontext/interface.py
sslcontext/utils.py
sslcontext/_vendor/__init__.py
sslcontext/_vendor/_utils.py
sslcontext/_vendor/imports.py
sslcontext/_vendor/pyopenssl.py
sslcontext/_vendor/ssl.py
sslcontext/_vendor/wait.py
sslcontext-1.4.3.dist-info/METADATA
sslcontext-1.4.3.dist-info/WHEEL
sslcontext-1.4.3.dist-info/top_level.txt
sslcontext-1.4.3.dist-info/RECORD
