Metadata-Version: 2.1
Name: sslcontext
Version: 1.4.3
Summary: Python x509 utilities to work load, dump a certificate, key and trust chain that can be used as credentials
Home-page: https://github.com/jose-pr/pypki
Author: Jose A.
Author-email: jose-pr@coqui.dev
License: UNKNOWN
Platform: UNKNOWN
Requires-Dist: idna ; extra == "idna"
Requires-Dist: pyopenssl ; extra == "pyopenssl"
Requires-Dist: wincertstore ; extra == "windows-alt-default-certs"
